collapsiblepane/__init__.py
collapsiblepane/collapsible_pane.py
collapsiblepane-0.10.30.dist-info/licenses/LICENSE
collapsiblepane-0.10.30.dist-info/METADATA
collapsiblepane-0.10.30.dist-info/WHEEL
collapsiblepane-0.10.30.dist-info/top_level.txt
collapsiblepane-0.10.30.dist-info/RECORD
