Metadata-Version: 2.4
Name: collapsiblepane
Version: 0.10.30
Summary: A PySide6 widget for collapsible panels, inspired by JavaFX's TitledPane
Author-email: Muhammad Junaid Khalid <mjk22071998@gmail.com>
License-Expression: MIT
Project-URL: Homepage, https://github.com/mjk22071998/CollapsiblePane
Project-URL: Repository, https://github.com/mjk22071998/CollapsiblePane
License-File: LICENSE
Requires-Dist: PySide6>=6.0
Dynamic: license-file
